miptlabs/__init__.py
miptlabs/config.py
miptlabs/approximators/__init__.py
miptlabs/approximators/base.py
miptlabs/approximators/experemental.py
miptlabs/approximators/functions.py
miptlabs/approximators/special.py
miptlabs/interpolators/__init__.py
miptlabs/interpolators/interpolators.py
miptlabs/interpolators/1133/__init__.py
miptlabs/latex/__init__.py
miptlabs/latex/representation.py
miptlabs/latex/tables.py
miptlabs/plotter/__init__.py
miptlabs/plotter/plotter.py
miptlabs/utils/__init__.py
miptlabs/utils/utils.py
miptlabs-1.0.17.1.data/data/readme.md
miptlabs-1.0.17.1.data/data/requirements.txt
miptlabs-1.0.17.1.dist-info/LICENSE
miptlabs-1.0.17.1.dist-info/METADATA
miptlabs-1.0.17.1.dist-info/WHEEL
miptlabs-1.0.17.1.dist-info/top_level.txt
miptlabs-1.0.17.1.dist-info/RECORD
