Metadata-Version: 2.1
Name: miptlabs
Version: 1.0.17.1
Summary: The package will help MIPT students to draw graphs easier
Home-page: https://github.com/dimon58/miptlabs
Author: Dmitry
License: UNKNOWN
Project-URL: Bug Tracker, https://github.com/dimon58/miptlabs/issues
Project-URL: Documentation, https://miptlabs.readthedocs.io/
Platform: UNKNOWN
Classifier: Programming Language :: Python :: 3
Classifier: License :: OSI Approved :: MIT License
Classifier: Operating System :: OS Independent
Requires-Python: >=3.6
License-File: LICENSE
Requires-Dist: matplotlib
Requires-Dist: numpy
Requires-Dist: scipy
Requires-Dist: pandas
Requires-Dist: statsmodels
